peaqevcore/__init__.py
peaqevcore/util.py
peaqevcore/common/average.py
peaqevcore/common/currency_translation.py
peaqevcore/common/trend.py
peaqevcore/common/wait_timer.py
peaqevcore/common/enums/calltype_enum.py
peaqevcore/common/enums/cautionhourtype.py
peaqevcore/common/models/observer_types.py
peaqevcore/common/models/peaq_system.py
peaqevcore/common/spotprice/__init__.py
peaqevcore/common/spotprice/const.py
peaqevcore/common/spotprice/dynamic_top_price.py
peaqevcore/common/spotprice/energidataservice.py
peaqevcore/common/spotprice/nordpool.py
peaqevcore/common/spotprice/spotprice_factory.py
peaqevcore/common/spotprice/spotpricebase.py
peaqevcore/common/spotprice/models/__init__.py
peaqevcore/common/spotprice/models/average_type.py
peaqevcore/common/spotprice/models/dynamic_top_price_model.py
peaqevcore/common/spotprice/models/spotprice_dto.py
peaqevcore/common/spotprice/models/spotprice_model.py
peaqevcore/common/spotprice/models/spotprice_type.py
peaqevcore/hub/__init__.py
peaqevcore/hub/killswitch.py
peaqevcore/models/__init__.py
peaqevcore/models/chargecontroller_states.py
peaqevcore/models/const.py
peaqevcore/models/fuses.py
peaqevcore/models/phases.py
peaqevcore/models/chargertype/__init__.py
peaqevcore/models/chargertype/calltype.py
peaqevcore/models/chargertype/charger_entities_model.py
peaqevcore/models/chargertype/charger_options.py
peaqevcore/models/chargertype/servicecalls_dto.py
peaqevcore/models/chargertype/servicecalls_options.py
peaqevcore/models/hourselection/__init__.py
peaqevcore/models/hourselection/hourselection_model.py
peaqevcore/models/hourselection/hourselection_options.py
peaqevcore/models/hourselection/set_top_price.py
peaqevcore/models/hourselection/topprice_type.py
peaqevcore/models/hourselection/hourobjects/__init__.py
peaqevcore/models/hourselection/hourobjects/hourobject.py
peaqevcore/models/hourselection/hourobjects/hourobject_helpers.py
peaqevcore/models/hub/__init__.py
peaqevcore/models/hub/carpowersensor.py
peaqevcore-19.11.4.dist-info/LICENSE
peaqevcore-19.11.4.dist-info/METADATA
peaqevcore-19.11.4.dist-info/WHEEL
peaqevcore-19.11.4.dist-info/top_level.txt
peaqevcore-19.11.4.dist-info/RECORD
