Metadata-Version: 2.2
Name: peaqevcore
Version: 19.11.4
Summary: Core types for peaqev car charging
Home-page: https://github.com/elden1337/peaqev-core
Author: Magnus Eldén
License: CC-NC-ND
License-File: LICENSE
Provides-Extra: tests
Requires-Dist: pytest>3.6.4; extra == "tests"
Requires-Dist: pytest-cov<2.6; extra == "tests"
Requires-Dist: pytest-asyncio; extra == "tests"
Dynamic: author
Dynamic: home-page
Dynamic: license
Dynamic: provides-extra
Dynamic: summary
